autobridge/__init__.py
autobridge/analyze.py
autobridge/dotgraph.py
autobridge/main.py
autobridge/util.py
autobridge/Codegen/Codegen.py
autobridge/Codegen/FIFOTemplate.py
autobridge/Codegen/FloorplanTclGeneration.py
autobridge/Codegen/InjectPipelineLogic.py
autobridge/Codegen/PipeliningControl.py
autobridge/Codegen/PipeliningFIFO.py
autobridge/Codegen/__init__.py
autobridge/Device/DeviceManager.py
autobridge/Device/__init__.py
autobridge/Floorplan/Bipartition.py
autobridge/Floorplan/EightWayPartition.py
autobridge/Floorplan/FourWayPartition.py
autobridge/Floorplan/ILPUtilities.py
autobridge/Floorplan/IterativeBipartion.py
autobridge/Floorplan/LegalizeFloorplan.py
autobridge/Floorplan/Partition.py
autobridge/Floorplan/Utilities.py
autobridge/Floorplan/__init__.py
autobridge/Flow/Manager.py
autobridge/Flow/__init__.py
autobridge/HLSParser/AXIConnectionParser.py
autobridge/HLSParser/__init__.py
autobridge/HLSParser/tapa/DataflowGraphTapa.py
autobridge/HLSParser/tapa/ProgramJsonManager.py
autobridge/HLSParser/tapa/__init__.py
autobridge/HLSParser/vivado_hls/HLSProjectManager.py
autobridge/HLSParser/vivado_hls/TopRTLParser.py
autobridge/HLSParser/vivado_hls/__init__.py
autobridge/Opt/Common.py
autobridge/Opt/DataflowGraph.py
autobridge/Opt/Floorplan.py
autobridge/Opt/FloorplanLegalize.py
autobridge/Opt/GlobalRouting.py
autobridge/Opt/LatencyBalancing.py
autobridge/Opt/Slot.py
autobridge/Opt/SlotManager.py
autobridge/Opt/__init__.py
autobridge/Route/__init__.py
autobridge/Route/global_route.py
autobridge/Route/latency_balancing.py
autobridge-0.0.20220512.dev1.dist-info/LICENSE
autobridge-0.0.20220512.dev1.dist-info/METADATA
autobridge-0.0.20220512.dev1.dist-info/WHEEL
autobridge-0.0.20220512.dev1.dist-info/top_level.txt
autobridge-0.0.20220512.dev1.dist-info/RECORD
