Metadata-Version: 2.1
Name: autobridge
Version: 0.0.20220512.dev1
Summary: AutoBridge
Home-page: https://github.com/Licheng-Guo/AutoBridge
Author: Licheng Guo
Classifier: Development Status :: 2 - Pre-Alpha
Classifier: Intended Audience :: Developers
Classifier: Intended Audience :: Science/Research
Classifier: Programming Language :: Python :: 3 :: Only
Classifier: Programming Language :: Python :: 3
Classifier: Programming Language :: Python :: 3.6
Classifier: Programming Language :: Python :: 3.7
Classifier: Programming Language :: Python :: 3.8
Classifier: Programming Language :: Python :: 3.9
Classifier: Topic :: System :: Hardware
Requires-Python: >=3.6
License-File: LICENSE
Requires-Dist: mip
Requires-Dist: pyverilog
Requires-Dist: prettytable
